README.md
setup.cfg
setup.py
pyreload/__init__.py
python_reload.egg-info/PKG-INFO
python_reload.egg-info/SOURCES.txt
python_reload.egg-info/dependency_links.txt
python_reload.egg-info/top_level.txt