Metadata-Version: 2.1
Name: python-reload
Version: 0.1-0
Summary: A module that allows you to make changes to a running python script and reload it
Home-page: https://github.com/febdaynik/PyReload
Author: Feb
Author-email: drons_dron@mail.ru
License: MIT
Platform: UNKNOWN
